{
  "generated_at": "2026-06-25T08:20:07.684885+00:00",
  "gsc_id": "04-14",
  "packet_kind": "missing_series",
  "candidate_source_strategy": "schuessler_k_tokens",
  "candidate_source_tokens": [
    "994"
  ],
  "schuessler": {
    "gsc_id": "04-14",
    "rhyme_section": 4,
    "series_number": 14,
    "k_tokens": [
      "994"
    ],
    "has_explicit_k_range": false,
    "source_remainder_raw": "Mand.         MC           LHan              OCM",
    "is_cross_reference_only": false,
    "source_page_number": 120,
    "source_line_number": 12,
    "source_line_raw": "4-14 = K. 994         Mand.         MC           LHan              OCM"
  },
  "coverage": {
    "gsc_id": "04-14",
    "rhyme_section": "4",
    "series_number": "14",
    "schuessler_k_tokens": "994",
    "schuessler_source_page": "120",
    "schuessler_cross_reference_only": "no",
    "in_tex": "no",
    "tex_character_count": "0",
    "tex_characters_sample": null,
    "mand2mc_row_count": "2",
    "mand2mc_character_count": "2",
    "mand2mc_characters_sample": "丘; 蚯",
    "bs_gsr_row_count": "2",
    "bs_gsr_character_count": "2",
    "bs_gsr_characters_sample": "丘; 蚯",
    "combined_source_character_count": "2",
    "combined_source_characters_sample": "丘; 蚯"
  },
  "tex_entry": null,
  "entry_hierarchy": null,
  "candidate_characters": [
    {
      "character": "丘",
      "in_tex": false,
      "mand2mc_rows": [
        {
          "source_row_number": "7306",
          "character": "丘",
          "pinyin": "qiu1",
          "mc_nwh": "khiuw",
          "mc_bs": "khjuw",
          "gsr": "0994a"
        }
      ],
      "bs_gsr_rows": [
        {
          "source_page_number": "155",
          "character": "丘",
          "pinyin": "qiū",
          "mc_bs": "khjuw",
          "mc_analyzed": "(kh- + -juw A)",
          "oc_bs": "*kʷʰə {*[k]ʷʰə}",
          "gloss": "hill, mound",
          "gsr": "0994a",
          "unicode_utf16": "U+4E18"
        }
      ],
      "shengfu_character_rows": [
        {
          "source_row_number": "11112",
          "character": "丘",
          "phonetic_component": "丘",
          "component_level": "1",
          "secondary_component": null,
          "fanqie": "去鳩",
          "source": "广韵",
          "oc_initial": "kʰ",
          "oc_rhyme": "ɯ",
          "oc_syllable": "kʰɯ"
        }
      ],
      "shengfu_component_rows": [
        {
          "source_row_number": "11112",
          "character": "丘",
          "phonetic_component": "丘",
          "component_level": "1",
          "secondary_component": null,
          "fanqie": "去鳩",
          "source": "广韵",
          "oc_initial": "kʰ",
          "oc_rhyme": "ɯ",
          "oc_syllable": "kʰɯ"
        },
        {
          "source_row_number": "11113",
          "character": "蚯",
          "phonetic_component": "丘",
          "component_level": "1",
          "secondary_component": null,
          "fanqie": "去鳩",
          "source": "广韵",
          "oc_initial": "kʰ",
          "oc_rhyme": "ɯ",
          "oc_syllable": "kʰɯ"
        },
        {
          "source_row_number": "11114",
          "character": "邱",
          "phonetic_component": "丘",
          "component_level": "1",
          "secondary_component": null,
          "fanqie": "去鳩",
          "source": "广韵",
          "oc_initial": "kʰ",
          "oc_rhyme": "ɯ",
          "oc_syllable": "kʰɯ"
        }
      ],
      "mc_resolution": {
        "status": "mand2mc-authoritative",
        "authoritative_source": "mand2mc",
        "display_forms": [
          "khiuw"
        ],
        "mand2mc_nwh_forms": [
          "khiuw"
        ],
        "mand2mc_bs_forms": [
          "khjuw"
        ],
        "bs_gsr_forms": [
          "khjuw"
        ],
        "bs_not_in_mand2mc": [],
        "mand2mc_not_in_bs_gsr": [],
        "needs_investigation": false
      },
      "mand_bs_mc_disagreement": false
    },
    {
      "character": "蚯",
      "in_tex": false,
      "mand2mc_rows": [
        {
          "source_row_number": "7307",
          "character": "蚯",
          "pinyin": "qiu1",
          "mc_nwh": "khiuw",
          "mc_bs": "khjuw",
          "gsr": "0994d"
        }
      ],
      "bs_gsr_rows": [
        {
          "source_page_number": "156",
          "character": "蚯",
          "pinyin": "qiū",
          "mc_bs": "khjuw",
          "mc_analyzed": "(kh- + -juw A)",
          "oc_bs": "*kʷʰə {*[k]ʷʰə}",
          "gloss": "earth-worm (khjuw.yinX)",
          "gsr": "0994d",
          "unicode_utf16": "U+86AF"
        }
      ],
      "shengfu_character_rows": [
        {
          "source_row_number": "11113",
          "character": "蚯",
          "phonetic_component": "丘",
          "component_level": "1",
          "secondary_component": null,
          "fanqie": "去鳩",
          "source": "广韵",
          "oc_initial": "kʰ",
          "oc_rhyme": "ɯ",
          "oc_syllable": "kʰɯ"
        }
      ],
      "shengfu_component_rows": [],
      "mc_resolution": {
        "status": "mand2mc-authoritative",
        "authoritative_source": "mand2mc",
        "display_forms": [
          "khiuw"
        ],
        "mand2mc_nwh_forms": [
          "khiuw"
        ],
        "mand2mc_bs_forms": [
          "khjuw"
        ],
        "bs_gsr_forms": [
          "khjuw"
        ],
        "bs_not_in_mand2mc": [],
        "mand2mc_not_in_bs_gsr": [],
        "needs_investigation": false
      },
      "mand_bs_mc_disagreement": false
    }
  ],
  "source_rows": {
    "mand2mc": [
      {
        "source_row_number": "7306",
        "character": "丘",
        "pinyin": "qiu1",
        "mc_nwh": "khiuw",
        "mc_bs": "khjuw",
        "gsr": "0994a"
      },
      {
        "source_row_number": "7307",
        "character": "蚯",
        "pinyin": "qiu1",
        "mc_nwh": "khiuw",
        "mc_bs": "khjuw",
        "gsr": "0994d"
      }
    ],
    "bs_gsr": [
      {
        "source_page_number": "155",
        "character": "丘",
        "pinyin": "qiū",
        "mc_bs": "khjuw",
        "mc_analyzed": "(kh- + -juw A)",
        "oc_bs": "*kʷʰə {*[k]ʷʰə}",
        "gloss": "hill, mound",
        "gsr": "0994a",
        "unicode_utf16": "U+4E18"
      },
      {
        "source_page_number": "156",
        "character": "蚯",
        "pinyin": "qiū",
        "mc_bs": "khjuw",
        "mc_analyzed": "(kh- + -juw A)",
        "oc_bs": "*kʷʰə {*[k]ʷʰə}",
        "gloss": "earth-worm (khjuw.yinX)",
        "gsr": "0994d",
        "unicode_utf16": "U+86AF"
      }
    ]
  },
  "notes": [
    "Machine-assembled curation packet; preserve all evidence and review before merging into main.tex.",
    "Do not treat candidate character lists or source matches as settled editorial decisions."
  ]
}
