{
  "generated_at": "2026-06-23T09:58:15.054492+00:00",
  "gsc_id": "05-10",
  "packet_kind": "missing_series",
  "candidate_source_strategy": "schuessler_k_tokens",
  "candidate_source_tokens": [
    "957"
  ],
  "schuessler": {
    "gsc_id": "05-10",
    "rhyme_section": 5,
    "series_number": 10,
    "k_tokens": [
      "957"
    ],
    "has_explicit_k_range": false,
    "source_remainder_raw": "Man d.          MC               LHan        OCM",
    "is_cross_reference_only": false,
    "source_page_number": 133,
    "source_line_number": 33,
    "source_line_raw": "5-10    = K. 957       Man d.          MC               LHan        OCM"
  },
  "coverage": {
    "gsc_id": "05-10",
    "rhyme_section": "5",
    "series_number": "10",
    "schuessler_k_tokens": "957",
    "schuessler_source_page": "133",
    "in_tex": "no",
    "tex_character_count": "0",
    "tex_characters_sample": null,
    "mand2mc_row_count": "11",
    "mand2mc_character_count": "9",
    "mand2mc_characters_sample": "意; 噫; 鷾; 醷; 億; 憶; 檍; 繶; 臆",
    "bs_gsr_row_count": "4",
    "bs_gsr_character_count": "4",
    "bs_gsr_characters_sample": "意; 億; 憶; 臆",
    "combined_source_character_count": "9",
    "combined_source_characters_sample": "意; 噫; 鷾; 醷; 億; 憶; 檍; 繶; 臆"
  },
  "tex_entry": null,
  "entry_hierarchy": null,
  "candidate_characters": [
    {
      "character": "意",
      "in_tex": false,
      "mand2mc_rows": [
        {
          "source_row_number": "7071",
          "character": "意",
          "pinyin": "yi4",
          "mc_nwh": "qiH",
          "mc_bs": "'iH",
          "gsr": "0957a"
        }
      ],
      "bs_gsr_rows": [
        {
          "source_page_number": "151",
          "character": "意",
          "pinyin": "yì",
          "mc_bs": "'iH",
          "mc_analyzed": "('- + -i C)",
          "oc_bs": "*ʔək-s {*ʔ(r)ək-s}",
          "gloss": "thought (n.)",
          "gsr": "0957a",
          "unicode_utf16": "U+610F"
        }
      ],
      "shengfu_character_rows": [
        {
          "source_row_number": "15690",
          "character": "意",
          "phonetic_component": "𠶷",
          "component_level": "1",
          "secondary_component": null,
          "fanqie": "於記",
          "source": "广韵",
          "oc_initial": "q",
          "oc_rhyme": "ɯɡs",
          "oc_syllable": "qɯɡs"
        }
      ],
      "shengfu_component_rows": [],
      "mc_resolution": {
        "status": "mand2mc-authoritative",
        "authoritative_source": "mand2mc",
        "display_forms": [
          "qiH"
        ],
        "mand2mc_nwh_forms": [
          "qiH"
        ],
        "mand2mc_bs_forms": [
          "'iH"
        ],
        "bs_gsr_forms": [
          "'iH"
        ],
        "bs_not_in_mand2mc": [],
        "mand2mc_not_in_bs_gsr": [],
        "needs_investigation": false
      },
      "mand_bs_mc_disagreement": false
    },
    {
      "character": "噫",
      "in_tex": false,
      "mand2mc_rows": [
        {
          "source_row_number": "7072",
          "character": "噫",
          "pinyin": "yi1",
          "mc_nwh": "qeayH",
          "mc_bs": "'eajH",
          "gsr": "0957b"
        },
        {
          "source_row_number": "7073",
          "character": "噫",
          "pinyin": "yi1",
          "mc_nwh": "qi",
          "mc_bs": "'i",
          "gsr": "0957b"
        }
      ],
      "bs_gsr_rows": [],
      "shengfu_character_rows": [
        {
          "source_row_number": "15676",
          "character": "噫",
          "phonetic_component": "𠶷",
          "component_level": "1",
          "secondary_component": null,
          "fanqie": "於其",
          "source": "广韵",
          "oc_initial": "q",
          "oc_rhyme": "ɯ",
          "oc_syllable": "qɯ"
        },
        {
          "source_row_number": "15689",
          "character": "噫",
          "phonetic_component": "𠶷",
          "component_level": "1",
          "secondary_component": null,
          "fanqie": "烏界",
          "source": "广韵",
          "oc_initial": "qʳ",
          "oc_rhyme": "ɯ̠ɡs",
          "oc_syllable": "qʳɯ̠ɡs"
        }
      ],
      "shengfu_component_rows": [],
      "mc_resolution": {
        "status": "mand2mc-authoritative",
        "authoritative_source": "mand2mc",
        "display_forms": [
          "qeayH",
          "qi"
        ],
        "mand2mc_nwh_forms": [
          "qeayH",
          "qi"
        ],
        "mand2mc_bs_forms": [
          "'eajH",
          "'i"
        ],
        "bs_gsr_forms": [],
        "bs_not_in_mand2mc": [],
        "mand2mc_not_in_bs_gsr": [],
        "needs_investigation": false
      },
      "mand_bs_mc_disagreement": false
    },
    {
      "character": "鷾",
      "in_tex": false,
      "mand2mc_rows": [
        {
          "source_row_number": "7074",
          "character": "鷾",
          "pinyin": "yi4",
          "mc_nwh": "qiH",
          "mc_bs": "'iH",
          "gsr": "0957c"
        }
      ],
      "bs_gsr_rows": [],
      "shengfu_character_rows": [
        {
          "source_row_number": "15691",
          "character": "鷾",
          "phonetic_component": "𠶷",
          "component_level": "1",
          "secondary_component": null,
          "fanqie": "於記",
          "source": "广韵",
          "oc_initial": "qʳ",
          "oc_rhyme": "ɯɡs",
          "oc_syllable": "qʳɯɡs"
        }
      ],
      "shengfu_component_rows": [],
      "mc_resolution": {
        "status": "mand2mc-authoritative",
        "authoritative_source": "mand2mc",
        "display_forms": [
          "qiH"
        ],
        "mand2mc_nwh_forms": [
          "qiH"
        ],
        "mand2mc_bs_forms": [
          "'iH"
        ],
        "bs_gsr_forms": [],
        "bs_not_in_mand2mc": [],
        "mand2mc_not_in_bs_gsr": [],
        "needs_investigation": false
      },
      "mand_bs_mc_disagreement": false
    },
    {
      "character": "醷",
      "in_tex": false,
      "mand2mc_rows": [
        {
          "source_row_number": "7075",
          "character": "醷",
          "pinyin": "yi4",
          "mc_nwh": "qik",
          "mc_bs": "'ik",
          "gsr": "0957d"
        },
        {
          "source_row_number": "7076",
          "character": "醷",
          "pinyin": "yi4",
          "mc_nwh": "qiX",
          "mc_bs": "'iX",
          "gsr": "0957d"
        }
      ],
      "bs_gsr_rows": [],
      "shengfu_character_rows": [
        {
          "source_row_number": "15678",
          "character": "醷",
          "phonetic_component": "𠶷",
          "component_level": "1",
          "secondary_component": null,
          "fanqie": "於擬",
          "source": "广韵",
          "oc_initial": "q",
          "oc_rhyme": "ɯʔ",
          "oc_syllable": "qɯʔ"
        },
        {
          "source_row_number": "15684",
          "character": "醷",
          "phonetic_component": "𠶷",
          "component_level": "1",
          "secondary_component": null,
          "fanqie": "於力",
          "source": "广韵",
          "oc_initial": "q",
          "oc_rhyme": "ɯɡ",
          "oc_syllable": "qɯɡ"
        }
      ],
      "shengfu_component_rows": [],
      "mc_resolution": {
        "status": "mand2mc-authoritative",
        "authoritative_source": "mand2mc",
        "display_forms": [
          "qik",
          "qiX"
        ],
        "mand2mc_nwh_forms": [
          "qik",
          "qiX"
        ],
        "mand2mc_bs_forms": [
          "'ik",
          "'iX"
        ],
        "bs_gsr_forms": [],
        "bs_not_in_mand2mc": [],
        "mand2mc_not_in_bs_gsr": [],
        "needs_investigation": false
      },
      "mand_bs_mc_disagreement": false
    },
    {
      "character": "億",
      "in_tex": false,
      "mand2mc_rows": [
        {
          "source_row_number": "7077",
          "character": "億",
          "pinyin": "yi4",
          "mc_nwh": "qik",
          "mc_bs": "'ik",
          "gsr": "0957e"
        }
      ],
      "bs_gsr_rows": [
        {
          "source_page_number": "151",
          "character": "億",
          "pinyin": "yì",
          "mc_bs": "'ik",
          "mc_analyzed": "('- + -ik D)",
          "oc_bs": "*ʔək {*ʔ(r)ək}",
          "gloss": "100000",
          "gsr": "0957e",
          "unicode_utf16": "U+5104"
        }
      ],
      "shengfu_character_rows": [
        {
          "source_row_number": "15680",
          "character": "億",
          "phonetic_component": "𠶷",
          "component_level": "1",
          "secondary_component": null,
          "fanqie": "於力",
          "source": "广韵",
          "oc_initial": "q",
          "oc_rhyme": "ɯɡ",
          "oc_syllable": "qɯɡ"
        }
      ],
      "shengfu_component_rows": [],
      "mc_resolution": {
        "status": "mand2mc-authoritative",
        "authoritative_source": "mand2mc",
        "display_forms": [
          "qik"
        ],
        "mand2mc_nwh_forms": [
          "qik"
        ],
        "mand2mc_bs_forms": [
          "'ik"
        ],
        "bs_gsr_forms": [
          "'ik"
        ],
        "bs_not_in_mand2mc": [],
        "mand2mc_not_in_bs_gsr": [],
        "needs_investigation": false
      },
      "mand_bs_mc_disagreement": false
    },
    {
      "character": "憶",
      "in_tex": false,
      "mand2mc_rows": [
        {
          "source_row_number": "7078",
          "character": "憶",
          "pinyin": "yi4",
          "mc_nwh": "qik",
          "mc_bs": "'ik",
          "gsr": "0957f"
        }
      ],
      "bs_gsr_rows": [
        {
          "source_page_number": "151",
          "character": "憶",
          "pinyin": "yì",
          "mc_bs": "'ik",
          "mc_analyzed": "('- + -ik D)",
          "oc_bs": "*ʔək {*ʔ(r)ək}",
          "gloss": "remember",
          "gsr": "0957f",
          "unicode_utf16": "U+61B6"
        }
      ],
      "shengfu_character_rows": [
        {
          "source_row_number": "15679",
          "character": "憶",
          "phonetic_component": "𠶷",
          "component_level": "1",
          "secondary_component": null,
          "fanqie": "於力",
          "source": "广韵",
          "oc_initial": "q",
          "oc_rhyme": "ɯɡ",
          "oc_syllable": "qɯɡ"
        }
      ],
      "shengfu_component_rows": [],
      "mc_resolution": {
        "status": "mand2mc-authoritative",
        "authoritative_source": "mand2mc",
        "display_forms": [
          "qik"
        ],
        "mand2mc_nwh_forms": [
          "qik"
        ],
        "mand2mc_bs_forms": [
          "'ik"
        ],
        "bs_gsr_forms": [
          "'ik"
        ],
        "bs_not_in_mand2mc": [],
        "mand2mc_not_in_bs_gsr": [],
        "needs_investigation": false
      },
      "mand_bs_mc_disagreement": false
    },
    {
      "character": "檍",
      "in_tex": false,
      "mand2mc_rows": [
        {
          "source_row_number": "7079",
          "character": "檍",
          "pinyin": "yi4",
          "mc_nwh": "qik",
          "mc_bs": "'ik",
          "gsr": "0957g"
        }
      ],
      "bs_gsr_rows": [],
      "shengfu_character_rows": [
        {
          "source_row_number": "15687",
          "character": "檍",
          "phonetic_component": "𠶷",
          "component_level": "1",
          "secondary_component": null,
          "fanqie": "於力",
          "source": "广韵",
          "oc_initial": "q",
          "oc_rhyme": "ɯɡ",
          "oc_syllable": "qɯɡ"
        }
      ],
      "shengfu_component_rows": [],
      "mc_resolution": {
        "status": "mand2mc-authoritative",
        "authoritative_source": "mand2mc",
        "display_forms": [
          "qik"
        ],
        "mand2mc_nwh_forms": [
          "qik"
        ],
        "mand2mc_bs_forms": [
          "'ik"
        ],
        "bs_gsr_forms": [],
        "bs_not_in_mand2mc": [],
        "mand2mc_not_in_bs_gsr": [],
        "needs_investigation": false
      },
      "mand_bs_mc_disagreement": false
    },
    {
      "character": "繶",
      "in_tex": false,
      "mand2mc_rows": [
        {
          "source_row_number": "7080",
          "character": "繶",
          "pinyin": "yi4",
          "mc_nwh": "qik",
          "mc_bs": "'ik",
          "gsr": "0957h"
        }
      ],
      "bs_gsr_rows": [],
      "shengfu_character_rows": [
        {
          "source_row_number": "15683",
          "character": "繶",
          "phonetic_component": "𠶷",
          "component_level": "1",
          "secondary_component": null,
          "fanqie": "於力",
          "source": "广韵",
          "oc_initial": "q",
          "oc_rhyme": "ɯɡ",
          "oc_syllable": "qɯɡ"
        }
      ],
      "shengfu_component_rows": [],
      "mc_resolution": {
        "status": "mand2mc-authoritative",
        "authoritative_source": "mand2mc",
        "display_forms": [
          "qik"
        ],
        "mand2mc_nwh_forms": [
          "qik"
        ],
        "mand2mc_bs_forms": [
          "'ik"
        ],
        "bs_gsr_forms": [],
        "bs_not_in_mand2mc": [],
        "mand2mc_not_in_bs_gsr": [],
        "needs_investigation": false
      },
      "mand_bs_mc_disagreement": false
    },
    {
      "character": "臆",
      "in_tex": false,
      "mand2mc_rows": [
        {
          "source_row_number": "7081",
          "character": "臆",
          "pinyin": "yi4",
          "mc_nwh": "qik",
          "mc_bs": "'ik",
          "gsr": "0957i"
        }
      ],
      "bs_gsr_rows": [
        {
          "source_page_number": "151",
          "character": "臆",
          "pinyin": "yì",
          "mc_bs": "'ik",
          "mc_analyzed": "('- + -ik D)",
          "oc_bs": "*ʔək {*ʔ(r)ək}",
          "gloss": "bosom",
          "gsr": "0957i",
          "unicode_utf16": "U+81C6"
        }
      ],
      "shengfu_character_rows": [
        {
          "source_row_number": "15681",
          "character": "臆",
          "phonetic_component": "𠶷",
          "component_level": "1",
          "secondary_component": null,
          "fanqie": "於力",
          "source": "广韵",
          "oc_initial": "q",
          "oc_rhyme": "ɯɡ",
          "oc_syllable": "qɯɡ"
        }
      ],
      "shengfu_component_rows": [],
      "mc_resolution": {
        "status": "mand2mc-authoritative",
        "authoritative_source": "mand2mc",
        "display_forms": [
          "qik"
        ],
        "mand2mc_nwh_forms": [
          "qik"
        ],
        "mand2mc_bs_forms": [
          "'ik"
        ],
        "bs_gsr_forms": [
          "'ik"
        ],
        "bs_not_in_mand2mc": [],
        "mand2mc_not_in_bs_gsr": [],
        "needs_investigation": false
      },
      "mand_bs_mc_disagreement": false
    }
  ],
  "source_rows": {
    "mand2mc": [
      {
        "source_row_number": "7071",
        "character": "意",
        "pinyin": "yi4",
        "mc_nwh": "qiH",
        "mc_bs": "'iH",
        "gsr": "0957a"
      },
      {
        "source_row_number": "7072",
        "character": "噫",
        "pinyin": "yi1",
        "mc_nwh": "qeayH",
        "mc_bs": "'eajH",
        "gsr": "0957b"
      },
      {
        "source_row_number": "7073",
        "character": "噫",
        "pinyin": "yi1",
        "mc_nwh": "qi",
        "mc_bs": "'i",
        "gsr": "0957b"
      },
      {
        "source_row_number": "7074",
        "character": "鷾",
        "pinyin": "yi4",
        "mc_nwh": "qiH",
        "mc_bs": "'iH",
        "gsr": "0957c"
      },
      {
        "source_row_number": "7075",
        "character": "醷",
        "pinyin": "yi4",
        "mc_nwh": "qik",
        "mc_bs": "'ik",
        "gsr": "0957d"
      },
      {
        "source_row_number": "7076",
        "character": "醷",
        "pinyin": "yi4",
        "mc_nwh": "qiX",
        "mc_bs": "'iX",
        "gsr": "0957d"
      },
      {
        "source_row_number": "7077",
        "character": "億",
        "pinyin": "yi4",
        "mc_nwh": "qik",
        "mc_bs": "'ik",
        "gsr": "0957e"
      },
      {
        "source_row_number": "7078",
        "character": "憶",
        "pinyin": "yi4",
        "mc_nwh": "qik",
        "mc_bs": "'ik",
        "gsr": "0957f"
      },
      {
        "source_row_number": "7079",
        "character": "檍",
        "pinyin": "yi4",
        "mc_nwh": "qik",
        "mc_bs": "'ik",
        "gsr": "0957g"
      },
      {
        "source_row_number": "7080",
        "character": "繶",
        "pinyin": "yi4",
        "mc_nwh": "qik",
        "mc_bs": "'ik",
        "gsr": "0957h"
      },
      {
        "source_row_number": "7081",
        "character": "臆",
        "pinyin": "yi4",
        "mc_nwh": "qik",
        "mc_bs": "'ik",
        "gsr": "0957i"
      }
    ],
    "bs_gsr": [
      {
        "source_page_number": "151",
        "character": "意",
        "pinyin": "yì",
        "mc_bs": "'iH",
        "mc_analyzed": "('- + -i C)",
        "oc_bs": "*ʔək-s {*ʔ(r)ək-s}",
        "gloss": "thought (n.)",
        "gsr": "0957a",
        "unicode_utf16": "U+610F"
      },
      {
        "source_page_number": "151",
        "character": "億",
        "pinyin": "yì",
        "mc_bs": "'ik",
        "mc_analyzed": "('- + -ik D)",
        "oc_bs": "*ʔək {*ʔ(r)ək}",
        "gloss": "100000",
        "gsr": "0957e",
        "unicode_utf16": "U+5104"
      },
      {
        "source_page_number": "151",
        "character": "憶",
        "pinyin": "yì",
        "mc_bs": "'ik",
        "mc_analyzed": "('- + -ik D)",
        "oc_bs": "*ʔək {*ʔ(r)ək}",
        "gloss": "remember",
        "gsr": "0957f",
        "unicode_utf16": "U+61B6"
      },
      {
        "source_page_number": "151",
        "character": "臆",
        "pinyin": "yì",
        "mc_bs": "'ik",
        "mc_analyzed": "('- + -ik D)",
        "oc_bs": "*ʔək {*ʔ(r)ək}",
        "gloss": "bosom",
        "gsr": "0957i",
        "unicode_utf16": "U+81C6"
      }
    ]
  },
  "notes": [
    "Machine-assembled curation packet; preserve all evidence and review before merging into main.tex.",
    "Do not treat candidate character lists or source matches as settled editorial decisions."
  ]
}
